{
  "3841288": "❌ SIN PREMIO, PROBA EN LA PRÓXIMA CARGA",
  "5239817": "❌ SIN PREMIO, PROBA EN LA PRÓXIMA CARGA",
  "6277735": "❌ SIN PREMIO, PROBA EN LA PRÓXIMA CARGA",
  "5296077": "❌ SIN PREMIO, PROBA EN LA PRÓXIMA CARGA",
  "3273277": "❌ SIN PREMIO, PROBA EN LA PRÓXIMA CARGA",
  "9209233": "❌ SIN PREMIO, PROBA EN LA PRÓXIMA CARGA",
  "1429501": "❌ SIN PREMIO, PROBA EN LA PRÓXIMA CARGA",
  "2849258": "❌ SIN PREMIO, PROBA EN LA PRÓXIMA CARGA",
  "9507153": "❌ SIN PREMIO, PROBA EN LA PRÓXIMA CARGA",
  "1861667": "❌ SIN PREMIO, PROBA EN LA PRÓXIMA CARGA",
  "9471022": "❌ SIN PREMIO, PROBA EN LA PRÓXIMA CARGA",
  "1764279": "❌ SIN PREMIO, PROBA EN LA PRÓXIMA CARGA",
  "4663745": "❌ SIN PREMIO, PROBA EN LA PRÓXIMA CARGA",
  "7792445": "❌ SIN PREMIO, PROBA EN LA PRÓXIMA CARGA",
  "3141289": "❌ SIN PREMIO, PROBA EN LA PRÓXIMA CARGA",
  "3527772": "❌ SIN PREMIO, PROBA EN LA PRÓXIMA CARGA",
  "2431572": "❌ SIN PREMIO, PROBA EN LA PRÓXIMA CARGA",
  "1447928": "❌ SIN PREMIO, PROBA EN LA PRÓXIMA CARGA",
  "9281497": "❌ SIN PREMIO, PROBA EN LA PRÓXIMA CARGA",
  "8299920": "❌ SIN PREMIO, PROBA EN LA PRÓXIMA CARGA",
  "9373566": "❌ SIN PREMIO, PROBA EN LA PRÓXIMA CARGA",
  "3699160": "❌ SIN PREMIO, PROBA EN LA PRÓXIMA CARGA",
  "8352314": "❌ SIN PREMIO, PROBA EN LA PRÓXIMA CARGA",
  "1038313": "❌ SIN PREMIO, PROBA EN LA PRÓXIMA CARGA",
  "1022205": "❌ SIN PREMIO, PROBA EN LA PRÓXIMA CARGA",
  "7280850": "❌ SIN PREMIO, PROBA EN LA PRÓXIMA CARGA",
  "5162798": "❌ SIN PREMIO, PROBA EN LA PRÓXIMA CARGA",
  "5976205": "❌ SIN PREMIO, PROBA EN LA PRÓXIMA CARGA",
  "6956245": "❌ SIN PREMIO, PROBA EN LA PRÓXIMA CARGA",
  "3189935": "❌ SIN PREMIO, PROBA EN LA PRÓXIMA CARGA",
  "2178880": "❌ SIN PREMIO, PROBA EN LA PRÓXIMA CARGA",
  "9837528": "❌ SIN PREMIO, PROBA EN LA PRÓXIMA CARGA",
  "5458230": "❌ SIN PREMIO, PROBA EN LA PRÓXIMA CARGA",
  "1991799": "❌ SIN PREMIO, PROBA EN LA PRÓXIMA CARGA",
  "1404440": "❌ SIN PREMIO, PROBA EN LA PRÓXIMA CARGA",
  "8541651": "❌ SIN PREMIO, PROBA EN LA PRÓXIMA CARGA",
  "4083900": "❌ SIN PREMIO, PROBA EN LA PRÓXIMA CARGA",
  "9640711": "❌ SIN PREMIO, PROBA EN LA PRÓXIMA CARGA",
  "3333027": "❌ SIN PREMIO, PROBA EN LA PRÓXIMA CARGA",
  "3865660": "❌ SIN PREMIO, PROBA EN LA PRÓXIMA CARGA",
  "8282954": "❌ SIN PREMIO, PROBA EN LA PRÓXIMA CARGA",
  "4430624": "❌ SIN PREMIO, PROBA EN LA PRÓXIMA CARGA",
  "7937727": "❌ SIN PREMIO, PROBA EN LA PRÓXIMA CARGA",
  "9719279": "❌ SIN PREMIO, PROBA EN LA PRÓXIMA CARGA",
  "1859605": "❌ SIN PREMIO, PROBA EN LA PRÓXIMA CARGA",
  "3383351": "❌ SIN PREMIO, PROBA EN LA PRÓXIMA CARGA",
  "1608372": "❌ SIN PREMIO, PROBA EN LA PRÓXIMA CARGA",
  "1155449": "❌ SIN PREMIO, PROBA EN LA PRÓXIMA CARGA",
  "8423203": "❌ SIN PREMIO, PROBA EN LA PRÓXIMA CARGA",
  "4795292": "❌ SIN PREMIO, PROBA EN LA PRÓXIMA CARGA",
  "2256470": "❌ SIN PREMIO, PROBA EN LA PRÓXIMA CARGA",
  "1176608": "❌ SIN PREMIO, PROBA EN LA PRÓXIMA CARGA",
  "9272501": "❌ SIN PREMIO, PROBA EN LA PRÓXIMA CARGA",
  "5950596": "❌ SIN PREMIO, PROBA EN LA PRÓXIMA CARGA",
  "4779497": "❌ SIN PREMIO, PROBA EN LA PRÓXIMA CARGA",
  "9109586": "❌ SIN PREMIO, PROBA EN LA PRÓXIMA CARGA",
  "2691716": "❌ SIN PREMIO, PROBA EN LA PRÓXIMA CARGA",
  "6947404": "❌ SIN PREMIO, PROBA EN LA PRÓXIMA CARGA",
  "5503006": "❌ SIN PREMIO, PROBA EN LA PRÓXIMA CARGA",
  "4716655": "❌ SIN PREMIO, PROBA EN LA PRÓXIMA CARGA",
  "1221078": "❌ SIN PREMIO, PROBA EN LA PRÓXIMA CARGA",
  "5332266": "❌ SIN PREMIO, PROBA EN LA PRÓXIMA CARGA",
  "3411579": "❌ SIN PREMIO, PROBA EN LA PRÓXIMA CARGA",
  "3493574": "❌ SIN PREMIO, PROBA EN LA PRÓXIMA CARGA",
  "2007592": "❌ SIN PREMIO, PROBA EN LA PRÓXIMA CARGA",
  "6125691": "❌ SIN PREMIO, PROBA EN LA PRÓXIMA CARGA",
  "9698601": "❌ SIN PREMIO, PROBA EN LA PRÓXIMA CARGA",
  "3061675": "❌ SIN PREMIO, PROBA EN LA PRÓXIMA CARGA",
  "9611002": "❌ SIN PREMIO, PROBA EN LA PRÓXIMA CARGA",
  "6097893": "❌ SIN PREMIO, PROBA EN LA PRÓXIMA CARGA",
  "9139030": "❌ SIN PREMIO, PROBA EN LA PRÓXIMA CARGA",
  "9899203": "❌ SIN PREMIO, PROBA EN LA PRÓXIMA CARGA",
  "3883482": "❌ SIN PREMIO, PROBA EN LA PRÓXIMA CARGA",
  "8746101": "❌ SIN PREMIO, PROBA EN LA PRÓXIMA CARGA",
  "5661288": "❌ SIN PREMIO, PROBA EN LA PRÓXIMA CARGA",
  "5467990": "❌ SIN PREMIO, PROBA EN LA PRÓXIMA CARGA",
  "7917698": "❌ SIN PREMIO, PROBA EN LA PRÓXIMA CARGA",
  "1048251": "❌ SIN PREMIO, PROBA EN LA PRÓXIMA CARGA",
  "7330482": "❌ SIN PREMIO, PROBA EN LA PRÓXIMA CARGA",
  "8441369": "❌ SIN PREMIO, PROBA EN LA PRÓXIMA CARGA",
  "8738979": "❌ SIN PREMIO, PROBA EN LA PRÓXIMA CARGA",
  "6800735": "❌ SIN PREMIO, PROBA EN LA PRÓXIMA CARGA",
  "1011770": "❌ SIN PREMIO, PROBA EN LA PRÓXIMA CARGA",
  "4566939": "❌ SIN PREMIO, PROBA EN LA PRÓXIMA CARGA",
  "5942060": "❌ SIN PREMIO, PROBA EN LA PRÓXIMA CARGA",
  "8003454": "❌ SIN PREMIO, PROBA EN LA PRÓXIMA CARGA",
  "6406686": "❌ SIN PREMIO, PROBA EN LA PRÓXIMA CARGA",
  "7858308": "❌ SIN PREMIO, PROBA EN LA PRÓXIMA CARGA",
  "2482711": "❌ SIN PREMIO, PROBA EN LA PRÓXIMA CARGA",
  "6045878": "❌ SIN PREMIO, PROBA EN LA PRÓXIMA CARGA",
  "4841649": "❌ SIN PREMIO, PROBA EN LA PRÓXIMA CARGA",
  "2599827": "❌ SIN PREMIO, PROBA EN LA PRÓXIMA CARGA",
  "4305422": "❌ SIN PREMIO, PROBA EN LA PRÓXIMA CARGA",
  "6290413": "❌ SIN PREMIO, PROBA EN LA PRÓXIMA CARGA",
  "9635646": "❌ SIN PREMIO, PROBA EN LA PRÓXIMA CARGA",
  "2463805": "❌ SIN PREMIO, PROBA EN LA PRÓXIMA CARGA",
  "2029482": "❌ SIN PREMIO, PROBA EN LA PRÓXIMA CARGA",
  "9716858": "❌ SIN PREMIO, PROBA EN LA PRÓXIMA CARGA",
  "7468752": "❌ SIN PREMIO, PROBA EN LA PRÓXIMA CARGA",
  "7107225": "❌ SIN PREMIO, PROBA EN LA PRÓXIMA CARGA",
  "3747435": "❌ SIN PREMIO, PROBA EN LA PRÓXIMA CARGA",
  "8941140": "❌ SIN PREMIO, PROBA EN LA PRÓXIMA CARGA",
  "3838165": "❌ SIN PREMIO, PROBA EN LA PRÓXIMA CARGA",
  "2596491": "❌ SIN PREMIO, PROBA EN LA PRÓXIMA CARGA",
  "5373468": "❌ SIN PREMIO, PROBA EN LA PRÓXIMA CARGA",
  "9573230": "❌ SIN PREMIO, PROBA EN LA PRÓXIMA CARGA",
  "4412279": "❌ SIN PREMIO, PROBA EN LA PRÓXIMA CARGA",
  "1463040": "❌ SIN PREMIO, PROBA EN LA PRÓXIMA CARGA",
  "2610793": "❌ SIN PREMIO, PROBA EN LA PRÓXIMA CARGA",
  "6729285": "❌ SIN PREMIO, PROBA EN LA PRÓXIMA CARGA",
  "5851328": "❌ SIN PREMIO, PROBA EN LA PRÓXIMA CARGA",
  "7176039": "❌ SIN PREMIO, PROBA EN LA PRÓXIMA CARGA",
  "3375936": "❌ SIN PREMIO, PROBA EN LA PRÓXIMA CARGA",
  "9681330": "❌ SIN PREMIO, PROBA EN LA PRÓXIMA CARGA",
  "1139814": "❌ SIN PREMIO, PROBA EN LA PRÓXIMA CARGA",
  "3976038": "❌ SIN PREMIO, PROBA EN LA PRÓXIMA CARGA",
  "4309119": "❌ SIN PREMIO, PROBA EN LA PRÓXIMA CARGA",
  "6104356": "❌ SIN PREMIO, PROBA EN LA PRÓXIMA CARGA",
  "1635011": "❌ SIN PREMIO, PROBA EN LA PRÓXIMA CARGA",
  "5387973": "❌ SIN PREMIO, PROBA EN LA PRÓXIMA CARGA",
  "2795471": "❌ SIN PREMIO, PROBA EN LA PRÓXIMA CARGA",
  "9340246": "❌ SIN PREMIO, PROBA EN LA PRÓXIMA CARGA",
  "7333521": "❌ SIN PREMIO, PROBA EN LA PRÓXIMA CARGA",
  "5610179": "❌ SIN PREMIO, PROBA EN LA PRÓXIMA CARGA",
  "4846692": "❌ SIN PREMIO, PROBA EN LA PRÓXIMA CARGA",
  "7702872": "❌ SIN PREMIO, PROBA EN LA PRÓXIMA CARGA",
  "6371199": "❌ SIN PREMIO, PROBA EN LA PRÓXIMA CARGA",
  "3641947": "❌ SIN PREMIO, PROBA EN LA PRÓXIMA CARGA",
  "2332754": "❌ SIN PREMIO, PROBA EN LA PRÓXIMA CARGA",
  "2999054": "❌ SIN PREMIO, PROBA EN LA PRÓXIMA CARGA",
  "1061542": "❌ SIN PREMIO, PROBA EN LA PRÓXIMA CARGA",
  "8814398": "❌ SIN PREMIO, PROBA EN LA PRÓXIMA CARGA",
  "2331864": "❌ SIN PREMIO, PROBA EN LA PRÓXIMA CARGA",
  "5520874": "❌ SIN PREMIO, PROBA EN LA PRÓXIMA CARGA",
  "9940036": "❌ SIN PREMIO, PROBA EN LA PRÓXIMA CARGA",
  "8315358": "❌ SIN PREMIO, PROBA EN LA PRÓXIMA CARGA",
  "7863414": "❌ SIN PREMIO, PROBA EN LA PRÓXIMA CARGA",
  "8825146": "❌ SIN PREMIO, PROBA EN LA PRÓXIMA CARGA",
  "8718923": "❌ SIN PREMIO, PROBA EN LA PRÓXIMA CARGA",
  "2165323": "❌ SIN PREMIO, PROBA EN LA PRÓXIMA CARGA",
  "1010950": "❌ SIN PREMIO, PROBA EN LA PRÓXIMA CARGA",
  "6300815": "❌ SIN PREMIO, PROBA EN LA PRÓXIMA CARGA",
  "3568412": "❌ SIN PREMIO, PROBA EN LA PRÓXIMA CARGA",
  "9464490": "❌ SIN PREMIO, PROBA EN LA PRÓXIMA CARGA",
  "8972638": "❌ SIN PREMIO, PROBA EN LA PRÓXIMA CARGA",
  "1534466": "❌ SIN PREMIO, PROBA EN LA PRÓXIMA CARGA",
  "7164589": "❌ SIN PREMIO, PROBA EN LA PRÓXIMA CARGA",
  "7909545": "❌ SIN PREMIO, PROBA EN LA PRÓXIMA CARGA",
  "2130475": "❌ SIN PREMIO, PROBA EN LA PRÓXIMA CARGA",
  "1097322": "❌ SIN PREMIO, PROBA EN LA PRÓXIMA CARGA",
  "8135477": "❌ SIN PREMIO, PROBA EN LA PRÓXIMA CARGA",
  "7896838": "❌ SIN PREMIO, PROBA EN LA PRÓXIMA CARGA",
  "6882182": "❌ SIN PREMIO, PROBA EN LA PRÓXIMA CARGA",
  "3776621": "❌ SIN PREMIO, PROBA EN LA PRÓXIMA CARGA",
  "8457865": "❌ SIN PREMIO, PROBA EN LA PRÓXIMA CARGA",
  "4083905": "❌ SIN PREMIO, PROBA EN LA PRÓXIMA CARGA",
  "2694859": "❌ SIN PREMIO, PROBA EN LA PRÓXIMA CARGA",
  "3733981": "❌ SIN PREMIO, PROBA EN LA PRÓXIMA CARGA",
  "9919373": "❌ SIN PREMIO, PROBA EN LA PRÓXIMA CARGA",
  "4430592": "❌ SIN PREMIO, PROBA EN LA PRÓXIMA CARGA",
  "8288068": "❌ SIN PREMIO, PROBA EN LA PRÓXIMA CARGA",
  "4165609": "❌ SIN PREMIO, PROBA EN LA PRÓXIMA CARGA",
  "1074685": "❌ SIN PREMIO, PROBA EN LA PRÓXIMA CARGA",
  "6411532": "❌ SIN PREMIO, PROBA EN LA PRÓXIMA CARGA",
  "9023112": "❌ SIN PREMIO, PROBA EN LA PRÓXIMA CARGA",
  "9111769": "❌ SIN PREMIO, PROBA EN LA PRÓXIMA CARGA",
  "9596677": "❌ SIN PREMIO, PROBA EN LA PRÓXIMA CARGA",
  "6336813": "❌ SIN PREMIO, PROBA EN LA PRÓXIMA CARGA",
  "9529515": "❌ SIN PREMIO, PROBA EN LA PRÓXIMA CARGA",
  "4056235": "❌ SIN PREMIO, PROBA EN LA PRÓXIMA CARGA",
  "5763694": "❌ SIN PREMIO, PROBA EN LA PRÓXIMA CARGA",
  "6089568": "❌ SIN PREMIO, PROBA EN LA PRÓXIMA CARGA",
  "4574227": "❌ SIN PREMIO, PROBA EN LA PRÓXIMA CARGA",
  "3624306": "❌ SIN PREMIO, PROBA EN LA PRÓXIMA CARGA",
  "4186032": "❌ SIN PREMIO, PROBA EN LA PRÓXIMA CARGA",
  "4627567": "❌ SIN PREMIO, PROBA EN LA PRÓXIMA CARGA",
  "4307730": "❌ SIN PREMIO, PROBA EN LA PRÓXIMA CARGA",
  "3393555": "❌ SIN PREMIO, PROBA EN LA PRÓXIMA CARGA",
  "9025230": "❌ SIN PREMIO, PROBA EN LA PRÓXIMA CARGA",
  "1421578": "❌ SIN PREMIO, PROBA EN LA PRÓXIMA CARGA",
  "8486047": "❌ SIN PREMIO, PROBA EN LA PRÓXIMA CARGA",
  "3797162": "❌ SIN PREMIO, PROBA EN LA PRÓXIMA CARGA",
  "2613724": "❌ SIN PREMIO, PROBA EN LA PRÓXIMA CARGA",
  "5391709": "❌ SIN PREMIO, PROBA EN LA PRÓXIMA CARGA",
  "5288790": "❌ SIN PREMIO, PROBA EN LA PRÓXIMA CARGA",
  "7676953": "❌ SIN PREMIO, PROBA EN LA PRÓXIMA CARGA",
  "9516009": "❌ SIN PREMIO, PROBA EN LA PRÓXIMA CARGA",
  "6916058": "❌ SIN PREMIO, PROBA EN LA PRÓXIMA CARGA",
  "6792512": "❌ SIN PREMIO, PROBA EN LA PRÓXIMA CARGA",
  "7328633": "❌ SIN PREMIO, PROBA EN LA PRÓXIMA CARGA",
  "1482259": "❌ SIN PREMIO, PROBA EN LA PRÓXIMA CARGA",
  "1202045": "❌ SIN PREMIO, PROBA EN LA PRÓXIMA CARGA",
  "9778768": "❌ SIN PREMIO, PROBA EN LA PRÓXIMA CARGA",
  "9277064": "❌ SIN PREMIO, PROBA EN LA PRÓXIMA CARGA",
  "7231831": "❌ SIN PREMIO, PROBA EN LA PRÓXIMA CARGA",
  "3786522": "❌ SIN PREMIO, PROBA EN LA PRÓXIMA CARGA",
  "1061428": "❌ SIN PREMIO, PROBA EN LA PRÓXIMA CARGA",
  "6887432": "❌ SIN PREMIO, PROBA EN LA PRÓXIMA CARGA",
  "4810424": "❌ SIN PREMIO, PROBA EN LA PRÓXIMA CARGA",
  "3948449": "❌ SIN PREMIO, PROBA EN LA PRÓXIMA CARGA"
}
